{
  "unversionedId": "user/quickstart",
  "id": "user/quickstart",
  "title": "Quick Start",
  "description": "Let's begin with a Microservices example.",
  "source": "@site/i18n/en/docusaurus-plugin-content-docs/current/user/quickstart.md",
  "sourceDirName": "user",
  "slug": "/user/quickstart",
  "permalink": "/docs/user/quickstart",
  "draft": false,
  "tags": [],
  "version": "current",
  "frontMatter": {
    "title": "Quick Start",
    "keywords": [
      "Seata"
    ],
    "description": "Let's begin with a Microservices example."
  },
  "sidebar": "docs",
  "previous": {
    "title": "Seata FAQ",
    "permalink": "/docs/overview/faq"
  },
  "next": {
    "title": "The seata parameter configuration version 1.6.0",
    "permalink": "/docs/user/configurations"
  }
}