{
  "permalink": "/blog/seata-analysis-tcc-modular",
  "source": "@site/blog/seata-analysis-tcc-modular.md",
  "title": "Seata tcc 模块源码分析",
  "description": "一  .导读",
  "date": "2019-12-25T00:00:00.000Z",
  "formattedDate": "December 25, 2019",
  "tags": [],
  "readingTime": 10.08,
  "hasTruncateMarker": false,
  "authors": [
    {
      "name": "赵润泽"
    }
  ],
  "frontMatter": {
    "title": "Seata tcc 模块源码分析",
    "author": "赵润泽",
    "keywords": [
      "Seata、分布式事务"
    ],
    "date": "2019/12/25"
  },
  "prevItem": {
    "title": "Seata Community Meetup·杭州站",
    "permalink": "/blog/seata-meetup-hangzhou"
  },
  "nextItem": {
    "title": "Seata core 模块源码分析",
    "permalink": "/blog/seata-analysis-core-modular"
  }
}