{
  "permalink": "/blog/seata-ha-practice",
  "source": "@site/blog/seata-ha-practice.md",
  "title": "Seata 高可用部署实践",
  "description": "Seata 高可用部署实践",
  "date": "2020-04-10T00:00:00.000Z",
  "formattedDate": "April 10, 2020",
  "tags": [],
  "readingTime": 6.655,
  "hasTruncateMarker": false,
  "authors": [
    {
      "name": "helloworlde"
    }
  ],
  "frontMatter": {
    "hidden": true,
    "title": "Seata 高可用部署实践",
    "keywords": [
      "kubernetes",
      "ops"
    ],
    "description": "Seata 高可用部署实践",
    "author": "helloworlde",
    "date": "2020-04-10T00:00:00.000Z"
  },
  "prevItem": {
    "title": "Seata 极简入门",
    "permalink": "/blog/seata-quick-start"
  },
  "nextItem": {
    "title": "Seata config 模块源码分析",
    "permalink": "/blog/seata-analysis-config-modular"
  }
}